azpypkg36/__init__.py
azpypkg36/azpypkg36.py
azpypkg36-0.1.0.dist-info/LICENSE
azpypkg36-0.1.0.dist-info/WHEEL
azpypkg36-0.1.0.dist-info/METADATA
azpypkg36-0.1.0.dist-info/RECORD
