Metadata-Version: 2.1
Name: azpypkg36
Version: 0.1.0
Summary: AaronZ Learning Python Package
License: MIT
Author: AaronZ
Requires-Python: >=3.9,<4.0
Classifier: License :: OSI Approved :: MIT License
Classifier: Programming Language :: Python :: 3
Classifier: Programming Language :: Python :: 3.10
Classifier: Programming Language :: Python :: 3.9
